diversify/__init__.py
diversify/asyncutils.py
diversify/constants.py
diversify/genetic.py
diversify/main.py
diversify/session.py
diversify/types.py
diversify/utils.py
diversify-0.1.1.dist-info/entry_points.txt
diversify-0.1.1.dist-info/LICENSE
diversify-0.1.1.dist-info/WHEEL
diversify-0.1.1.dist-info/METADATA
diversify-0.1.1.dist-info/RECORD
