Metadata-Version: 2.1
Name: diversify
Version: 0.1.1
Summary: A small playlist generator for spotify
License: MIT
Author: Eduardo Macedo
Author-email: eduzemacedo@hotmail.com
Requires-Python: >=3.7,<4.0
Classifier: License :: OSI Approved :: MIT License
Classifier: Programming Language :: Python :: 3
Classifier: Programming Language :: Python :: 3.7
Classifier: Programming Language :: Python :: 3.8
Requires-Dist: aiohttp (>=3.6.2,<4.0.0)
Requires-Dist: click (>=7.1.2,<8.0.0)
Requires-Dist: colorama (>=0.4.3,<0.5.0)
Requires-Dist: numpy (>=1.19.2,<2.0.0)
Requires-Dist: pandas (>=1.1.2,<2.0.0)
Requires-Dist: spotipy (>=2.16.0,<3.0.0)
